Metadata-Version: 2.1
Name: Ziplag
Version: 0.0.2
Summary: For make python simple
Author: OneNc (Ziplag)
Author-email: <muhamadtriwanda@gmail.com>
Keywords: ziplag
Classifier: Development Status :: 5 - Production/Stable
Classifier: Intended Audience :: Education
Classifier: Operating System :: Microsoft :: Windows :: Windows 10
Classifier: Operating System :: Unix
Classifier: Operating System :: MacOS :: MacOS X
Classifier: License :: OSI Approved :: MIT License
Classifier: Programming Language :: Python :: 3
License-File: LICENSE
